{
  "schema_version": 1,
  "id": "paper-855e3c1d6c104bc0",
  "title": "Stretchable, self-healing, and processable bioelastomers enabled by highly branched cross-linking networks for flexible electronics",
  "authors": [
    "Yuan Liu",
    "Xin Xu",
    "Jinsong Sun",
    "Aojing Xue",
    "Jianing Liu",
    "Yuhan Lou",
    "Jiajun Liu",
    "Shi Liu",
    "Dan Sui",
    "Zhiyi Hou",
    "Gegu Chen",
    "Luyao Wang"
  ],
  "venue": "Research",
  "primary_category": "制造、封装与可靠性",
  "categories": [
    "制造、封装与可靠性",
    "柔性材料与器件"
  ],
  "strongly_related": false,
  "date": "2026-07-19",
  "doi": "10.34133/research.1391",
  "source_url": "https://doi.org/10.34133/research.1391",
  "pdf_source_url": "",
  "pdf_version": "unavailable",
  "pdf_version_label": "暂无可合法自动获取的开放全文",
  "status": "metadata_only_no_legal_pdf",
  "generated_at": "2026-07-22T01:06:00.671629+00:00",
  "page_count": 0,
  "abstract": {
    "original": "",
    "zh": "与柔性触觉相关，但尚未显示对前端触觉计算的直接贡献。当前未从摘要提取到可比较数值。"
  },
  "innovation_points": [
    "当前仅获得题录信息，需要打开 DOI/原文核实机制、实验和性能指标。",
    "与柔性触觉相关，但尚未显示对前端触觉计算的直接贡献"
  ],
  "innovation_suggestions": [],
  "inspirations": [
    "提供机器人、可穿戴或电子皮肤系统任务证据"
  ],
  "preparation_steps": [],
  "method_blocks": [],
  "figures": [],
  "original_pdf": "",
  "reader_markdown": "research-memory/literature/2026/2026-07-22/deep-reads/paper-855e3c1d6c104bc0/paper.md",
  "source_map": "",
  "notes": [
    "当前仅完成题录/摘要级筛选。",
    "未获得合法开放全文，因此不生成制备步骤、逐图解释或 PDF 副本。"
  ],
  "curation_status": "automatic_draft"
}
